obsidian_brain/__init__.py
obsidian_brain/enhanced_mind.py
obsidian_brain/server.py
obsidian_brain-0.1.3.dist-info/METADATA
obsidian_brain-0.1.3.dist-info/WHEEL
obsidian_brain-0.1.3.dist-info/entry_points.txt
obsidian_brain-0.1.3.dist-info/RECORD
