Metadata-Version: 2.3
Name: obsidian-brain
Version: 0.1.3
Summary: Give claude access to your obsidian brain
Author-email: spongeboi <hi@spongeboi.com>
Requires-Python: >=3.10
Requires-Dist: flagembedding>=1.3.2
Requires-Dist: httpx>=0.27.2
Requires-Dist: lancedb>=0.16.0
Requires-Dist: langchain-community>=0.3.8
Requires-Dist: langchain-core>=0.3.21
Requires-Dist: markdown>=3.7
Requires-Dist: mcp>=1.0.0
Requires-Dist: rank-bm25>=0.2.2
Requires-Dist: sentence-transformers>=3.3.1
Requires-Dist: unstructured>=0.16.8
Requires-Dist: watchfiles>=1.0.0
Requires-Dist: whoosh>=2.7.4
